src/__init__.py
src/aidd/__init__.py
src/aidd/cli.py
src/aidd/server.py
src/aidd/tools/__init__.py
src/aidd/tools/base.py
src/aidd/tools/code_analysis.py
src/aidd/tools/code_execution.py
src/aidd/tools/code_tools.py
src/aidd/tools/directory_tools.py
src/aidd/tools/file_tools.py
src/aidd/tools/get_active_apps_tool.py
src/aidd/tools/get_available_windows_tool.py
src/aidd/tools/git_tools.py
src/aidd/tools/image_tools.py
src/aidd/tools/lint_tools.py
src/aidd/tools/other_tools.py
src/aidd/tools/path_tools.py
src/aidd/tools/screenshot_tool.py
src/aidd/tools/state.py
src/aidd/tools/system_tools.py
src/aidd/tools/web_tools.py
orange2_skydeckai_code-0.1.34.dist-info/METADATA
orange2_skydeckai_code-0.1.34.dist-info/WHEEL
orange2_skydeckai_code-0.1.34.dist-info/entry_points.txt
orange2_skydeckai_code-0.1.34.dist-info/licenses/LICENSE
orange2_skydeckai_code-0.1.34.dist-info/RECORD
